mas_algo_cli/__init__.py
mas_algo_cli/cli.py
mas_algo_cli/runner.py
mas_algo_cli/commands/__init__.py
mas_algo_cli/commands/debug.py
mas_algo_cli/commands/install_deps.py
mas_algo_cli/commands/new.py
mas_algo_cli/commands/pack.py
mas_algo_cli/commands/run.py
mas_algo_cli/commands/stubs.py
mas_algo_cli/stubs/__init__.py
mas_algo_cli/stubs/pyproject.toml
mas_algo_cli/stubs/rest/__init__.py
mas_algo_cli/stubs/rest/process_base.py
mas_algo_cli/templates/__init__.py
mas_algo_cli/templates/basic/.env.example
mas_algo_cli/templates/basic/__init__.py
mas_algo_cli/templates/basic/main.py
mas_algo_cli/templates/basic/requirements.txt
mas_algo_cli/templates/basic/utils.py
mas_algo_cli/templates/cv/.env.example
mas_algo_cli/templates/cv/__init__.py
mas_algo_cli/templates/cv/main.py
mas_algo_cli/templates/cv/requirements.txt
mas_algo_cli/templates/cv/utils.py
mas_algo_cli/templates/predict/.env.example
mas_algo_cli/templates/predict/__init__.py
mas_algo_cli/templates/predict/main.py
mas_algo_cli/templates/predict/requirements.txt
mas_algo_cli/templates/predict/utils.py
mas_algo_cli-0.2.1.dist-info/METADATA
mas_algo_cli-0.2.1.dist-info/WHEEL
mas_algo_cli-0.2.1.dist-info/entry_points.txt
mas_algo_cli-0.2.1.dist-info/RECORD
