Metadata-Version: 2.4
Name: mas-algo-cli
Version: 0.2.1
Summary: CLI tool for managing MAS hosting platform algorithm services
License-Expression: MIT
Classifier: License :: OSI Approved :: MIT License
Classifier: Operating System :: OS Independent
Classifier: Programming Language :: Python :: 3
Classifier: Topic :: Software Development :: Build Tools
Requires-Python: ==3.9.*
Requires-Dist: debugpy>=1.8.0
